CONTRIBUTING.rst
LICENSE.txt
MANIFEST.in
README.md
pyproject.toml
requirements-dev.txt
requirements-setup.txt
requirements.txt
setup.cfg
setup.py
versioneer.py
bin/DatasetHierarchyReader.py
bin/GenerateInputCSV_Datasethierarchy.py
bin/GenerateInputCSV_Filename.py
bin/resampleMask.py
bin/testParams.py
data/README.md
data/brain1_image.nrrd
data/brain1_label.nrrd
data/brain2_image.nrrd
data/brain2_label.nrrd
data/breast1_image.nrrd
data/breast1_label.nrrd
data/lung1_image.nrrd
data/lung1_label.nrrd
data/lung2_image.nrrd
data/lung2_label.nrrd
data/baseline/baseline_firstorder.csv
data/baseline/baseline_glcm.csv
data/baseline/baseline_gldm.csv
data/baseline/baseline_glrlm.csv
data/baseline/baseline_glszm.csv
data/baseline/baseline_ngtdm.csv
data/baseline/baseline_shape.csv
data/baseline/baseline_shape2D.csv
data/baseline/brain1_glcm.npy
data/baseline/brain1_gldm.npy
data/baseline/brain1_glrlm.npy
data/baseline/brain1_glszm.npy
data/baseline/brain1_ngtdm.npy
data/baseline/brain2_glcm.npy
data/baseline/brain2_gldm.npy
data/baseline/brain2_glrlm.npy
data/baseline/brain2_glszm.npy
data/baseline/brain2_ngtdm.npy
data/baseline/breast1_glcm.npy
data/baseline/breast1_gldm.npy
data/baseline/breast1_glrlm.npy
data/baseline/breast1_glszm.npy
data/baseline/breast1_ngtdm.npy
data/baseline/lung1_glcm.npy
data/baseline/lung1_gldm.npy
data/baseline/lung1_glrlm.npy
data/baseline/lung1_glszm.npy
data/baseline/lung1_ngtdm.npy
data/baseline/lung2_glcm.npy
data/baseline/lung2_gldm.npy
data/baseline/lung2_glrlm.npy
data/baseline/lung2_glszm.npy
data/baseline/lung2_ngtdm.npy
data/baseline/wavelet.npy
examples/batchProcessingWithPandas.py
examples/batchprocessing.py
examples/batchprocessing_parallel.py
examples/helloFeatureClass.py
examples/helloRadiomics.py
examples/helloRadiomicsWithSettings.py
examples/helloResampling.py
examples/helloVoxel.py
examples/testCases.csv
examples/exampleSettings/MR_2D_extraction.yaml
examples/exampleSettings/Params.yaml
examples/exampleSettings/exampleCT.yaml
pyradiomics_bhklab.egg-info/PKG-INFO
pyradiomics_bhklab.egg-info/SOURCES.txt
pyradiomics_bhklab.egg-info/dependency_links.txt
pyradiomics_bhklab.egg-info/entry_points.txt
pyradiomics_bhklab.egg-info/not-zip-safe
pyradiomics_bhklab.egg-info/requires.txt
pyradiomics_bhklab.egg-info/top_level.txt
