Metadata-Version: 2.1
Name: pyradiomics-bhklab
Version: 3.1.4
Summary: Radiomics features library for python
Author-email: PyRadiomics Community <pyradiomics@googlegroups.com>
License: Copyright 2017 Harvard Medical School
Project-URL: Homepaget, http://github.com/AIM-Harvard/pyradiomics#readme
Project-URL: Radiomics.io, https://www.radiomics.io/
Project-URL: Documentation, https://pyradiomics.readthedocs.io/en/latest/index.html
Project-URL: Docker, https://hub.docker.com/r/radiomics/pyradiomics/
Project-URL: Github, https://github.com/AIM-Harvard/pyradiomics
Keywords: radiomics,cancerimaging,medicalresearch,computationalimaging
Classifier: Development Status :: 5 - Production/Stable
Classifier: Environment :: Console
Classifier: Intended Audience :: Developers
Classifier: Intended Audience :: Science/Research
Classifier: License :: OSI Approved :: BSD License
Classifier: Operating System :: OS Independent
Classifier: Programming Language :: C
Classifier: Programming Language :: Python :: 3.5
Classifier: Programming Language :: Python :: 3.6
Classifier: Programming Language :: Python :: 3.7
Classifier: Programming Language :: Python :: 3.8
Classifier: Programming Language :: Python :: 3.9
Classifier: Topic :: Scientific/Engineering :: Bio-Informatics
Requires-Python: >=3.5
License-File: LICENSE.txt
Requires-Dist: numpy
Requires-Dist: SimpleITK
Requires-Dist: PyWavelets
Requires-Dist: pykwalify
Requires-Dist: six
Provides-Extra: build
Requires-Dist: auditwheel<7,>=6.1.0; extra == "build"
Requires-Dist: twine<6,>=5.1.1; extra == "build"
